helix_personmatching/__init__.py
helix_personmatching/nick_name_loader.py
helix_personmatching/nick_name_overrides.csv
helix_personmatching/py.typed
helix_personmatching/fhir_manager/__init__.py
helix_personmatching/fhir_manager/fhir_loader.py
helix_personmatching/fhir_manager/parse_name_result.py
helix_personmatching/fhir_manager/fhir_to_dict_manager/__init__.py
helix_personmatching/fhir_manager/fhir_to_dict_manager/fhir_to_dict_manager.py
helix_personmatching/fhir_manager/fhir_to_dict_manager/test/__init__.py
helix_personmatching/fhir_manager/fhir_to_dict_manager/test/test_fhir_to_dict_manager.py
helix_personmatching/logics/__init__.py
helix_personmatching/logics/match_score.py
helix_personmatching/logics/match_score_without_threshold.py
helix_personmatching/logics/rule_attribute_score.py
helix_personmatching/logics/rule_library.py
helix_personmatching/logics/rule_score.py
helix_personmatching/logics/rules_generator.py
helix_personmatching/logics/score_calculator.py
helix_personmatching/logics/scoring_input.py
helix_personmatching/matchers/__init__.py
helix_personmatching/matchers/matcher.py
helix_personmatching/matchers/test/__init__.py
helix_personmatching/matchers/test/exact_match/__init__.py
helix_personmatching/matchers/test/exact_match/test_exact_match.py
helix_personmatching/matchers/test/exact_match_bundle/__init__.py
helix_personmatching/matchers/test/exact_match_bundle/test_exact_match_bundle.py
helix_personmatching/matchers/test/exact_match_list/__init__.py
helix_personmatching/matchers/test/exact_match_list/test_exact_match_list.py
helix_personmatching/matchers/test/exact_match_long_id/__init__.py
helix_personmatching/matchers/test/exact_match_long_id/test_exact_match_long_id.py
helix_personmatching/matchers/test/exact_match_name_use_different/__init__.py
helix_personmatching/matchers/test/exact_match_name_use_different/test_exact_match_name_use_different.py
helix_personmatching/matchers/test/fail_different_first_name/__init__.py
helix_personmatching-1.0.63.dist-info/licenses/LICENSE
helix_personmatching-1.0.63.dist-info/METADATA
helix_personmatching-1.0.63.dist-info/WHEEL
helix_personmatching-1.0.63.dist-info/top_level.txt
helix_personmatching-1.0.63.dist-info/RECORD
