Metadata-Version: 2.4
Name: helix.personmatching
Version: 1.0.63
Summary: helix.personmatching
Home-page: https://github.com/icanbwell/helix.personmatching
Author: Imran Qureshi
Author-email: imran@icanbwell.com
Classifier: Development Status :: 4 - Beta
Classifier: Programming Language :: Python :: 3
Classifier: License :: OSI Approved :: Apache Software License
Classifier: Operating System :: OS Independent
Requires-Python: >=3.10
License-File: LICENSE
Requires-Dist: rapidfuzz>=3.9.4
Requires-Dist: orjson>=3.10.6
Requires-Dist: fhir.resources<8,>=7.1.0
Requires-Dist: usaddress>=0.5.10
Requires-Dist: usaddress-scourgify>=0.6.0
Requires-Dist: phonenumbers>=8.13.40
Requires-Dist: phonetics>=1.0.5
Requires-Dist: nominally>=1.1.0
Requires-Dist: nicknames>=1.0.0
Requires-Dist: requests
Requires-Dist: python-crfsuite>=0.9.11
Requires-Dist: torch<=2.8.0,>=2.5.0
Dynamic: author
Dynamic: author-email
Dynamic: classifier
Dynamic: description
Dynamic: description-content-type
Dynamic: home-page
Dynamic: license-file
Dynamic: requires-dist
Dynamic: requires-python
Dynamic: summary
